{
    "exercises": [{
            "exName": "Straight arm plank",
            "exType": "plank",
            "exInstructionsImgUrl": "Images/exercises/straight-plank.png"
        },
        {
            "exName": "Regular plank",
            "exType": "plank",
            "exInstructionsImgUrl": "Images/exercises/regular-plank.jpg"
        },
        {
            "exName": "Spiderman plank",
            "exType": "plank",
            "exInstructionsImgUrl": "Images/exercises/spiderman-plank.gif"
        },
        {
            "exName": "V-up hold",
            "exType": "plank",
            "exInstructionsImgUrl": "Images/exercises/v-up-hold.jpg"
        },
        {
            "exName": "Bridge hold",
            "exType": "plank",
            "exInstructionsImgUrl": "Images/exercises/bridge-hold.jpg"
        },
        {
            "exName": "Crunches",
            "exType": "core",
            "exInstructionsImgUrl": "Images/exercises/crunches.gif"
        },
        {
            "exName": "Reverse crunches",
            "exType": "core",
            "exInstructionsImgUrl": "Images/exercise/reverse-crunches.gif"
        },
        {
            "exName": "Bicycles",
            "exType": "core",
            "exInstructionsImgUrl": "Images/exercises/bicycles.gif"
        },
        {
            "exName": "V-ups",
            "exType": "core",
            "exInstructionsImgUrl": "Images/exercises/v-ups.gif"
        },
        {
            "exName": "Russian twists",
            "exType": "core",
            "exInstructionsImgUrl": "Images/exercises/russian-twists.gif"
        },
        {
            "exName": "Sit ups",
            "exType": "core",
            "exInstructionsImgUrl": "Images/exercises/sit-ups.gif"
        },
        {
            "exName": "Squats",
            "exType": "lower",
            "exInstructionsImgUrl": "Images/exercises/squats.gif"
        },
        {
            "exName": "Lunges",
            "exType": "lower",
            "exInstructionsImgUrl": "Images/exercises/lunges.gif"
        },
        {
            "exName": "Step up on chair",
            "exType": "lower",
            "exInstructionsImgUrl": "Images/exercises/step-up-on-chair.gif"
        },
        {
            "exName": "Bridge up",
            "exType": "lower",
            "exInstructionsImgUrl": "Images/exercises/bridge-ups.gif"
        },
        {
            "exName": "Side lunges",
            "exType": "lower",
            "exInstructionsImgUrl": "Images/exercises/side-lunges.gif"
        },
        {
            "exName": "Wall sit",
            "exType": "lower",
            "exInstructionsImgUrl": "Images/exercises/wall-sit.jpg"
        },
        {
            "exName": "Pushups",
            "exType": "upper",
            "exInstructionsImgUrl": "Images/exercises/pushups.gif"
        },
        {
            "exName": "Wide pushups",
            "exType": "upper",
            "exInstructionsImgUrl": "Images/exercises/wide-pushups.gif"
        },
        {
            "exName": "Tricep dips",
            "exType": "upper",
            "exInstructionsImgUrl": "Images/exercises/tricep-dips.gif"
        },
        {
            "exName": "Bird dog",
            "exType": "upper",
            "exInstructionsImgUrl": "Images/exercises/bird-dog.gif"
        },
        {
            "exName": "Knee pushups",
            "exType": "upper",
            "exInstructionsImgUrl": "Images/exercises/knee-pushups.gif"
        },
        {
            "exName": "Bear crawl",
            "exType": "upper",
            "exInstructionsImgUrl": "Images/exercises/bear-crawl.gif"
        },
        {
            "exName": "Jumping jacks",
            "exType": "fullBody",
            "exInstructionsImgUrl": "Images/exercises/jumping-jacks.gif"
        },
        {
            "exName": "Mountain climbers",
            "exType": "fullBody",
            "exInstructionsImgUrl": "Images/exercises/mountain-climbers.gif"
        },
        {
            "exName": "High knees running",
            "exType": "fullBody",
            "exInstructionsImgUrl": "Images/exercises/high-knees.gif"
        },
        {
            "exName": "Sun salutations",
            "exType": "fullBody",
            "exInstructionsImgUrl": "Images/exercises/sun-salutations.gif"
        },
        {
            "exName": "Spot jogging",
            "exType": "fullBody",
            "exInstructionsImgUrl": "Images/exercises/spot-jogging.gif"
        },
        {
            "exName": "Arms rotation",
            "exType": "fullBody",
            "exInstructionsImgUrl": "Images/exercises/arms-rotations.gif"
        }
    ]
}